CurrencyConverter/__init__.py
CurrencyConverter/__main__.py
PyLeb_CurrencyConverter-1.0.0.dist-info/LICENSE
PyLeb_CurrencyConverter-1.0.0.dist-info/METADATA
PyLeb_CurrencyConverter-1.0.0.dist-info/WHEEL
PyLeb_CurrencyConverter-1.0.0.dist-info/entry_points.txt
PyLeb_CurrencyConverter-1.0.0.dist-info/top_level.txt
PyLeb_CurrencyConverter-1.0.0.dist-info/RECORD
