Metadata-Version: 2.1
Name: PyLeb_CurrencyConverter
Version: 1.0.0
Summary: a library to  convert between currencies using  google server
Author-email: mesteranas <anasformohammed@gmail.com>
License: GNU GENERAL PUBLIC LICENSE
Project-URL: Homepage, https://github.com/mesteranas/PyLeb_CurrencyConverter
Keywords: currency,currencyConverter,PyLeb_CurrencyConverter
Classifier: Programming Language :: Python
Classifier: Programming Language :: Python :: 3
Requires-Python: >=3.9
License-File: LICENSE
Requires-Dist: requests
